oils/__init__.py
oils/geo/__init__.py
oils/geo/geo.py
oils-0.0.0.dist-info/METADATA
oils-0.0.0.dist-info/WHEEL
oils-0.0.0.dist-info/RECORD
