Metadata-Version: 2.1
Name: oils
Version: 0.0.0
Summary: Build numerical simulation with ease
Author: altar31
Author-email: damien.sicard31@gmail.com
Requires-Python: >=3.10,<4.0
Classifier: Programming Language :: Python :: 3
Classifier: Programming Language :: Python :: 3.10
Classifier: Programming Language :: Python :: 3.11
Requires-Dist: matplotlib (>=3.7.1,<4.0.0)
Requires-Dist: pygmsh (>=7.1.17,<8.0.0)
Requires-Dist: pytest (>=7.3.0,<8.0.0)
